calculations/__init__.py
calculations/segment_metrics.py
calculations/segment_metrics_test.py
calculations/columns/__init__.py
calculations/columns/breakout.py
calculations/columns/breakout_test.py
calculations/columns/breath.py
calculations/columns/dps.py
calculations/columns/dps_test.py
calculations/columns/in_time.py
calculations/columns/in_time_test.py
calculations/columns/kick.py
calculations/columns/kick_test.py
calculations/columns/lap_times.py
calculations/columns/lap_times_test.py
calculations/columns/out_time.py
calculations/columns/out_time_test.py
calculations/columns/segments.py
calculations/columns/segments_test.py
calculations/columns/split_time.py
calculations/columns/split_time_test.py
calculations/columns/stroke_rate.py
calculations/columns/stroke_rate_test.py
calculations/columns/strokes.py
calculations/columns/strokes_test.py
calculations/columns/turn_index.py
calculations/columns/turn_index_test.py
calculations/columns/velocity.py
calculations/columns/velocity_test.py
calculations/test_data/__init__.py
calculations/test_data/utils.py
calculations/types/__init__.py
calculations/types/enums/__init__.py
calculations/types/enums/ams_property.py
calculations/types/enums/stroke_types.py
calculations/types/services/__init__.py
calculations/types/services/calculations/__init__.py
calculations/types/services/calculations/corrected_annotation.py
calculations/types/services/calculations/lane.py
calculations/utils/__init__.py
calculations/utils/annotation.py
calculations/utils/annotation_test.py
calculations/utils/common.py
calculations/utils/common_test.py
calculations/utils/distance.py
calculations/utils/distance_test.py
calculations/utils/logging.py
calculations/utils/meter_time.py
calculations/utils/stroke_type.py
calculations/utils/stroke_type_test.py
calculations/utils/time.py
calculations/utils/time_test.py
spartaCalculation-0.0.31.dist-info/METADATA
spartaCalculation-0.0.31.dist-info/WHEEL
spartaCalculation-0.0.31.dist-info/top_level.txt
spartaCalculation-0.0.31.dist-info/RECORD
